fv3config/__init__.py
fv3config/_asset_list.py
fv3config/_datastore.py
fv3config/_exceptions.py
fv3config/_tables.py
fv3config/caching.py
fv3config/cli.py
fv3config/filesystem.py
fv3config/config/__init__.py
fv3config/config/_serialization.py
fv3config/config/alter.py
fv3config/config/default.py
fv3config/config/derive.py
fv3config/config/diag_table.py
fv3config/config/namelist.py
fv3config/config/nudging.py
fv3config/config/rundir.py
fv3config/config/time_constants.py
fv3config/config/types.py
fv3config/data/__init__.py
fv3config/data/data_table/data_table_default
fv3config/data/diag_table/diag_table_baroclinic
fv3config/data/diag_table/diag_table_default
fv3config/data/diag_table/diag_table_grid_spec
fv3config/data/diag_table/diag_table_no_output
fv3config/data/field_table/field_table_GFDLMP
fv3config/data/field_table/field_table_ZhaoCarr
fv3config/data/namelist/baroclinic.nml
fv3config/data/namelist/default.nml
fv3config/fv3run/__init__.py
fv3config/fv3run/__main__.py
fv3config/fv3run/_docker.py
fv3config/fv3run/_kubernetes.py
fv3config/fv3run/_native.py
fv3config/fv3run/_native_main.py
fv3config-0.9.0.dist-info/LICENSE
fv3config-0.9.0.dist-info/METADATA
fv3config-0.9.0.dist-info/WHEEL
fv3config-0.9.0.dist-info/entry_points.txt
fv3config-0.9.0.dist-info/top_level.txt
fv3config-0.9.0.dist-info/RECORD
