Metadata-Version: 2.1
Name: fv3config
Version: 0.9.0
Summary: FV3Config is used to configure and manipulate run directories for FV3GFS.
Home-page: https://github.com/ai2cm/fv3config
Author: Allen Institute of Artificial Intelligence
Author-email: jeremym@allenai.org
License: Apache 2.0 license
Keywords: fv3config
Platform: UNKNOWN
Classifier: Development Status :: 2 - Pre-Alpha
Classifier: Intended Audience :: Developers
Classifier: License :: OSI Approved :: Apache Software License
Classifier: Natural Language :: English
Classifier: Programming Language :: Python :: 3
Classifier: Programming Language :: Python :: 3.6
Classifier: Programming Language :: Python :: 3.7
Requires-Python: >=3.6
License-File: LICENSE
Requires-Dist: f90nml (>=1.1.0)
Requires-Dist: appdirs (>=1.4.0)
Requires-Dist: pyyaml (>=5.0)
Requires-Dist: gcsfs (>=0.7.0)
Requires-Dist: fsspec (>=0.8.0)
Requires-Dist: dacite (>=1.6.0)
Provides-Extra: bucket-access
Requires-Dist: gcsfs ; extra == 'bucket-access'
Provides-Extra: fv3run
Requires-Dist: fv3gfs-python ; extra == 'fv3run'
Provides-Extra: run_kubernetes
Requires-Dist: kubernetes ; extra == 'run_kubernetes'
